{
  "ts": "2026-05-26T14:20:34",
  "mode": "linear_probing",
  "run_name": "downstream_cmapss_rul_linear_probing",
  "dataset": "CMAPSS_RUL",
  "target_key": "rul_capped_125",
  "seed": 42,
  "git_hash": "86c73695721e044fc971366ac81ef5d6ee205848",
  "git_dirty": false,
  "config_hash": "51266c7ae9154e4d",
  "checkpoint_loaded": "/content/drive/MyDrive/fm_fl_phmd/checkpoints/ssl_central_full/ssl_central_full_patchtst_phm/ckpt_step100000.pt",
  "n_trainable_params": 129,
  "n_total_params": 801937,
  "batch_size_requested": 32,
  "batch_size_effective": 21,
  "batch_size_policy": "adaptive_by_channels",
  "n_channels": 24,
  "n_channels_source": "manifest",
  "max_channel_batch": 512,
  "min_batch_size": 1,
  "effective_bc": 504,
  "amp_used": true,
  "amp_nonfinite_grad_steps": 13,
  "best_epoch": 20,
  "best_value": 43.21395087460906,
  "metric_for_best": "rmse_val",
  "lower_is_better": true,
  "test_metrics": {
    "mae": 47.21167432695582,
    "rmse": 53.8626735214119,
    "r2": -1.1288152751729514,
    "cmapss_score": 1002484.8459673865,
    "n_samples": 6610
  },
  "elapsed_seconds": 428.2,
  "model": {
    "name": "patchtst_phm_base",
    "d_model": 128,
    "n_layers": 4,
    "n_heads": 4,
    "d_ff": 512,
    "dropout": 0.1,
    "patch_size": 16,
    "n_patches": 32
  },
  "training": {
    "max_epochs": 20,
    "lr_head": 0.001,
    "lr_backbone": null,
    "weight_decay": 0.01,
    "amp": "auto",
    "grad_clip_norm": 1.0,
    "log_every": 50,
    "eval_every_epochs": 1,
    "metric_for_best": "rmse_val",
    "lower_is_better": true,
    "max_train_batches_per_epoch": null,
    "max_val_batches": null,
    "max_test_batches": null
  },
  "head": {
    "hidden_dim": null,
    "dropout": 0.0,
    "activation": null,
    "keep_last_dim": false
  }
}
